MANIFEST.in
README
README.rst
setup.py
nose_setenv/__init__.py
nose_setenv/__init__.pyc
nose_setenv/nose_setenv.py
nose_setenv/nose_setenv.pyc
nose_setenv.egg-info/PKG-INFO
nose_setenv.egg-info/SOURCES.txt
nose_setenv.egg-info/dependency_links.txt
nose_setenv.egg-info/entry_points.txt
nose_setenv.egg-info/not-zip-safe
nose_setenv.egg-info/requires.txt
nose_setenv.egg-info/top_level.txt